yemot_ai/__init__.py
yemot_ai/core.py
yemot_ai/providers.py
yemot_ai/session_store.py
yemot_ai-0.1.1.dist-info/METADATA
yemot_ai-0.1.1.dist-info/WHEEL
yemot_ai-0.1.1.dist-info/licenses/LICENSE
yemot_ai-0.1.1.dist-info/RECORD
