Metadata-Version: 2.4
Name: yemot-ai
Version: 0.1.1
Summary: חבילת Python לחיבור סוכני AI למערכות ימות המשיח
Project-URL: Homepage, https://github.com/davidTheDeveloperY/yemot-ai
Project-URL: Repository, https://github.com/davidTheDeveloperY/yemot-ai
Project-URL: Documentation, https://github.com/davidTheDeveloperY/yemot-ai#readme
Project-URL: Issues, https://github.com/davidTheDeveloperY/yemot-ai/issues
Project-URL: Changelog, https://github.com/davidTheDeveloperY/yemot-ai/releases
Project-URL: Examples, https://github.com/davidTheDeveloperY/yemot-ai/tree/master/examples
Author-email: davidTheDeveloper <dev@code-chai.com>
License-File: LICENSE
Keywords: ai,codex,ivr,openai,telephony,voice,yemot
Classifier: Development Status :: 3 - Alpha
Classifier: Intended Audience :: Developers
Classifier: License :: OSI Approved :: MIT License
Classifier: Programming Language :: Python :: 3
Classifier: Programming Language :: Python :: 3.8
Classifier: Programming Language :: Python :: 3.9
Classifier: Programming Language :: Python :: 3.10
Classifier: Programming Language :: Python :: 3.11
Classifier: Programming Language :: Python :: 3.12
Classifier: Topic :: Communications :: Telephony
Classifier: Topic :: Software Development :: Libraries :: Python Modules
Requires-Python: >=3.8.1
Requires-Dist: yemot-flow
Provides-Extra: all
Requires-Dist: openai>=1.0.0; extra == 'all'
Requires-Dist: redis>=4.0.0; extra == 'all'
Provides-Extra: dev
Requires-Dist: black>=23.0; extra == 'dev'
Requires-Dist: flake8>=6.0; extra == 'dev'
Requires-Dist: pytest-cov>=4.0; extra == 'dev'
Requires-Dist: pytest>=7.0; extra == 'dev'
Provides-Extra: openai
Requires-Dist: openai>=1.0.0; extra == 'openai'
Provides-Extra: redis
Requires-Dist: redis>=4.0.0; extra == 'redis'
